next/__init__.py
next/apps.py
next/checks.py
next/forms.py
next/pages.py
next/urls.py
next/templatetags/__init__.py
next/templatetags/forms.py
next_dj-0.2.0.dist-info/METADATA
next_dj-0.2.0.dist-info/WHEEL
next_dj-0.2.0.dist-info/licenses/LICENSE
next_dj-0.2.0.dist-info/RECORD
