Metadata-Version: 2.4
Name: next.dj
Version: 0.2.0
Summary: Next-gen framework for Django developers
Project-URL: Homepage, https://github.com/next-dj/next-dj
Project-URL: Documentation, https://next-dj.readthedocs.io/
Project-URL: Repository, https://github.com/next-dj/next-dj
Project-URL: Bug Tracker, https://github.com/next-dj/next-dj/issues
License: MIT
License-File: LICENSE
Keywords: django,framework,frontend,low-code
Classifier: Development Status :: 3 - Alpha
Classifier: Framework :: Django
Classifier: Intended Audience :: Developers
Classifier: License :: OSI Approved :: MIT License
Classifier: Programming Language :: Python :: 3
Classifier: Programming Language :: Python :: 3.12
Classifier: Topic :: Software Development :: Libraries :: Python Modules
Requires-Python: >=3.12
Requires-Dist: django<6.1,>=4.2
